axiom_tc/Bootloader.py
axiom_tc/CDU_Common.py
axiom_tc/I2C_Comms.py
axiom_tc/SPI_Comms.py
axiom_tc/USB_Comms.py
axiom_tc/__init__.py
axiom_tc/axiom.py
axiom_tc/u02_SystemManager.py
axiom_tc/u06_SelfTest.py
axiom_tc/u07_LiveView.py
axiom_tc/u31_DeviceInformation.py
axiom_tc/u32_DeviceCapabilities.py
axiom_tc/u33_CRCData.py
axiom_tc/u48_GPIOControls.py
axiom_tc/uXX_Template.py
axiom_tc-4.9.3.0.dist-info/licenses/LICENSE
axiom_tc-4.9.3.0.dist-info/METADATA
axiom_tc-4.9.3.0.dist-info/WHEEL
axiom_tc-4.9.3.0.dist-info/top_level.txt
axiom_tc-4.9.3.0.dist-info/RECORD
