Metadata-Version: 2.4
Name: axiom_tc
Version: 4.9.3.0
Summary: Python library for TouchNetix aXiom Touch Controllers
Author-email: Mark Satterthwaite <mark.satterthwaite@touchnetix.com>, James Cameron <james.cameron@touchnetix.com>, Henry Spencer <henry.spencer@touchnetix.com>
License: MIT
Project-URL: Homepage, https://www.touchnetix.com/
Project-URL: Repository, https://github.com/TouchNetix/axiom_pylib
Classifier: Programming Language :: Python :: 3
Classifier: License :: OSI Approved :: MIT License
Classifier: Operating System :: OS Independent
Requires-Python: >=3.8
License-File: LICENSE
Dynamic: license-file
